ambient_wds/init.py
ambient_wds/main.py
ambient_wds-0.2.7.dist-info/licenses/LICENSE
ambient_wds-0.2.7.dist-info/METADATA
ambient_wds-0.2.7.dist-info/WHEEL
ambient_wds-0.2.7.dist-info/entry_points.txt
ambient_wds-0.2.7.dist-info/top_level.txt
ambient_wds-0.2.7.dist-info/RECORD
