Metadata-Version: 2.4
Name: ambient-wds
Version: 0.2.7
Summary: Ship weather data from Ambient Weather API to APRS-IS/aprs.fi
Author-email: "Jake Barbieur, N9DMT" <n9deltamiketango@gmail.com>
License: MIT License
Requires-Python: >=3.9
License-File: LICENSE
Requires-Dist: requests
Requires-Dist: pyyaml
Requires-Dist: click
Dynamic: license-file
